<?xml version="1.0"?>
<openerp>
    <data>
        <record model="ir.ui.view" id="crm_case_form_view_oppor">
            <field name="name">CRM - Opportunities - Quote Inherit</field>
            <field name="model">crm.lead</field>
            <field name="inherit_id" ref="sale_crm.crm_case_form_view_oppor"/>
            <field name="arch" type="xml">
                <data>
                    <xpath expr="//field[@name='stage_id']" position="before">
                        <button string="New Quotation" name="create_quotation_from_lead" type="object" class="oe_highlight"/>
                    </xpath>
                    <div name="button_box" position="inside">
                        <button class="oe_stat_button" type="action"
                                name="%(sale_crm.sale_action_quotations_new)d" icon="fa-usd"
                                context="{'default_partner_id': partner_id, 'search_default_draft': 1}">
                            <div class="o_stat_info">
<!--                                <field name="sale_number" class="o_stat_value"/>-->
                                <span class="o_stat_text"> Quote(s) </span>
                            </div>
                        </button>
                        <button class="oe_stat_button" type="action" attrs="{'invisible': [('sale_amount_total', '=', 0)]}"
                                name="%(sale_crm.sale_action_quotations_new)d" icon="fa-usd"
                                context="{'search_default_partner_id': partner_id, 'default_partner_id': partner_id, 'search_default_sales': 1}">
                            <div class="o_form_field o_stat_info">
                                <span class="o_stat_value"><field name="sale_amount_total" widget="monetary" options="{'currency_field': 'company_currency'}"/></span>
                                <span class="o_stat_text"> Orders</span>
                            </div>
                        </button>
                    </div>
                </data>
            </field>
        </record>

    </data>
</openerp>
